Metadata-Version: 2.4
Name: ableton-mcp-fastmcp
Version: 1.0.1
Summary: Ableton Live integration through the Model Context Protocol
Author-email: Siddharth Ahuja <ahujasid@gmail.com>
License: MIT
Project-URL: Homepage, https://github.com/fastmcp-me/ableton-mcp#readme
Project-URL: Repository, https://github.com/fastmcp-me/ableton-mcp.git
Project-URL: Issues, https://github.com/fastmcp-me/ableton-mcp/issues
Classifier: Programming Language :: Python :: 3
Classifier: License :: OSI Approved :: MIT License
Classifier: Operating System :: OS Independent
Requires-Python: >=3.10
License-File: LICENSE
Requires-Dist: mcp[cli]>=1.3.0
Dynamic: license-file
